[
    {
        "user": "U3ABVD72L",
        "text": "<@U3ABVD72L|alexander.bauer> has joined the channel",
        "type": "message",
        "subtype": "channel_join",
        "ts": "1481014478.000087"
    },
    {
        "user": "U3ADJU5MZ",
        "text": "<@U3ADJU5MZ|kansi> has joined the channel",
        "type": "message",
        "subtype": "channel_join",
        "ts": "1481018138.000088"
    },
    {
        "user": "U2FSX8RMY",
        "text": "<@U2FSX8RMY|palani.kodeswaran> has joined the channel",
        "type": "message",
        "subtype": "channel_join",
        "ts": "1481033762.000091"
    },
    {
        "user": "U2T7Z63NY",
        "text": "<@U2T7Z63NY|synblockchainteam> has joined the channel",
        "type": "message",
        "subtype": "channel_join",
        "ts": "1481036869.000092"
    },
    {
        "type": "message",
        "user": "U2T7Z63NY",
        "text": "Hi, Please let me know if this forum provides solutions regarding \"hyperledger v0.6\" related queries. Thanks.",
        "ts": "1481036873.000093"
    },
    {
        "type": "message",
        "user": "U3AFRMY68",
        "text": "Hi, I have a question regarding chaincode application architecture. (just picking a random example) Suppose I am an insurer and I want to write a insurance policy for cars chaincode. Considering the architecture, would I deploy a new chaincode for every car insurance I sell? or would one deployment of my chaincode handle all insurances of the same type?",
        "ts": "1481039133.000094"
    },
    {
        "type": "message",
        "user": "U2W7U5UA3",
        "text": "<@U2T7Z63NY> People here are pretty good at answering questions, although searching slack\/stackoverflow\/google may find you an answer first. Also note that this channel is specifically for chaincode, not \"hyperledger v0.6\" in general. What do you want to know?",
        "ts": "1481040077.000096"
    },
    {
        "type": "message",
        "user": "U2W7U5UA3",
        "text": "<@U3AFRMY68> You'd write your chaincode and deploy it once and then 'invoke' it each time you'd like to create a new policy through an SDK or REST call.",
        "ts": "1481040147.000097"
    },
    {
        "type": "message",
        "user": "U3AFRMY68",
        "text": "<@U2W7U5UA3> sounds fair enough, so that's what I would use the tables for I assume? Can I also store more complex datastructures? Like different fields with values for every 'contract' ?",
        "ts": "1481040252.000098"
    },
    {
        "type": "message",
        "user": "U2W7U5UA3",
        "text": "Yes, the tables\/states are where you store your data on the blockchain. You can make the table structure as complex as you like as far as I know.",
        "ts": "1481040507.000099"
    },
    {
        "type": "message",
        "user": "U2W7U5UA3",
        "text": "It's worth looking at IBM's learn-chaincode git\n<https:\/\/github.com\/IBM-Blockchain\/learn-chaincode>",
        "attachments": [
            {
                "service_name": "GitHub",
                "title": "IBM-Blockchain\/learn-chaincode",
                "title_link": "https:\/\/github.com\/IBM-Blockchain\/learn-chaincode",
                "text": "learn-chaincode - Learn how to write chaincode.",
                "fallback": "GitHub: IBM-Blockchain\/learn-chaincode",
                "thumb_url": "https:\/\/avatars2.githubusercontent.com\/u\/17178768?v=3&s=400",
                "from_url": "https:\/\/github.com\/IBM-Blockchain\/learn-chaincode",
                "thumb_width": 200,
                "thumb_height": 200,
                "service_icon": "https:\/\/github.com\/apple-touch-icon.png",
                "id": 1
            }
        ],
        "ts": "1481040541.000100"
    },
    {
        "type": "message",
        "user": "U2W7U5UA3",
        "text": "Also, this documentation has helped me a lot in developing my chaincode as it provides all the functions available in the shim package\n<https:\/\/godoc.org\/github.com\/hyperledger\/fabric\/core\/chaincode\/shim>",
        "attachments": [
            {
                "title": "Package shim",
                "title_link": "https:\/\/godoc.org\/github.com\/hyperledger\/fabric\/core\/chaincode\/shim",
                "text": "Package shim provides APIs for the chaincode to access its state variables, transaction context and call other chaincodes.",
                "fallback": "Package shim",
                "from_url": "https:\/\/godoc.org\/github.com\/hyperledger\/fabric\/core\/chaincode\/shim",
                "service_icon": "https:\/\/godoc.org\/favicon.ico",
                "service_name": "godoc.org",
                "id": 1
            }
        ],
        "ts": "1481040600.000102"
    },
    {
        "type": "message",
        "user": "U0ULK2JPP",
        "text": "<@U1ES70KQS>",
        "ts": "1481048065.000106"
    },
    {
        "type": "message",
        "user": "U1ES70KQS",
        "text": "sorry to clog up general",
        "ts": "1481048082.000107"
    },
    {
        "type": "message",
        "user": "U1ES70KQS",
        "text": "chaincode screen:",
        "ts": "1481048089.000108"
    },
    {
        "type": "message",
        "user": "U1ES70KQS",
        "text": "&gt; vagrant@hyperledger-devenv:v0.2.1-3533817:~\/fabric\/examples\/chaincode\/go\/chaincode_example02$ CORE_CHAINCODE_ID_NAME=mycc CORE_PEER_ADDRESS=0.0.0.0:7051 .\/chaincode_example02\n18:14:14.191 [shim] INFO : Chaincode log level not provided; defaulting to: DEBUG\n18:14:14.192 [shim] DEBU : Peer address: 0.0.0.0:7051\n18:14:14.196 [shim] DEBU : os.Args returns: [.\/chaincode_example02]\n18:14:14.198 [shim] DEBU : Registering.. sending REGISTER\n18:14:14.200 [shim] DEBU : []Received message REGISTERED from shim\n18:14:14.200 [shim] DEBU : []Handling ChaincodeMessage of type: REGISTERED(state:created)\n18:14:14.201 [shim] DEBU : Received REGISTERED, ready for invocations",
        "ts": "1481048092.000109"
    },
    {
        "type": "message",
        "user": "U0ULK2JPP",
        "text": "no worries\u2026 there\u2019s som much activity there...",
        "ts": "1481048103.000110"
    },
    {
        "type": "message",
        "user": "U0ULK2JPP",
        "text": "ok",
        "ts": "1481048111.000111"
    },
    {
        "type": "message",
        "user": "U0ULK2JPP",
        "text": "and your peer command line and the deploy command line too",
        "ts": "1481048131.000112"
    },
    {
        "type": "message",
        "user": "U1ES70KQS",
        "text": "peer:",
        "ts": "1481048158.000113"
    },
    {
        "type": "message",
        "user": "U1ES70KQS",
        "text": "&gt; vagrant@hyperledger-devenv:v0.2.1-3533817:~\/fabric$ peer node start --peer-chaincodedev\n18:12:52.001 [msp] func1 -&gt; INFO 001 Creating the msp manager\n18:12:52.001 [msp] GetManager -&gt; INFO 002 Returning MSP manager %!p(msp.peerMspManagerImpl={map[]  false})\n18:12:52.001 [msp] Setup -&gt; INFO 003 Setting up the MSP manager from config file \/opt\/gopath\/src\/github.com\/hyperledger\/fabric\/msp\/peer-config.json\n18:12:52.001 [msp] newBccspMsp -&gt; INFO 004 Creating BCCSP-based MSP instance\n18:12:52.001 [SW_BCCSP] createKeyStoreIfNotExists -&gt; INFO 005 KeyStore path [\/tmp] missing [false]: [&lt;clean&gt;]\n18:12:52.002 [msp] Setup -&gt; INFO 006 Setting up MSP DEFAULT\n...",
        "ts": "1481048162.000114"
    },
    {
        "type": "message",
        "user": "U0ULK2JPP",
        "text": "ko",
        "ts": "1481048174.000115"
    },
    {
        "type": "message",
        "user": "U0ULK2JPP",
        "text": "ok",
        "ts": "1481048175.000116"
    },
    {
        "type": "message",
        "user": "U1ES70KQS",
        "text": "usage:",
        "ts": "1481048178.000117"
    },
    {
        "type": "message",
        "user": "U1ES70KQS",
        "text": "&gt; vagrant@hyperledger-devenv:v0.2.1-3533817:~$ PEER_CHAINCODE_MODE=dev peer chaincode deploy -n mycc -c '{\"Args\": [\"init\", \"a\",\"100\", \"b\", \"200\"]}'\n18:15:02.708 [msp] func1 -&gt; INFO 001 Creating the msp manager\n18:15:02.709 [msp] GetManager -&gt; INFO 002 Returning MSP manager %!p(msp.peerMspManagerImpl={map[]  false})\n18:15:02.709 [msp] Setup -&gt; INFO 003 Setting up the MSP manager from config file \/opt\/gopath\/src\/github.com\/hyperledger\/fabric\/msp\/peer-config.json\n18:15:02.709 [msp] newBccspMsp -&gt; INFO 004 Creating BCCSP-based MSP instance\n18:15:02.709 [SW_BCCSP] createKeyStoreIfNotExists -&gt; INFO 005 KeyStore path [\/tmp] missing [false]: [&lt;clean&gt;]\n18:15:02.709 [msp] Setup -&gt; INFO 006 Setting up MSP DEFAULT\n18:15:02.709 [msp] Setup -&gt; INFO 007 Setting up MSP instance from file \/opt\/gopath\/src\/github.com\/hyperledger\/fabric\/msp\/peer-config.json\n18:15:02.730 [msp] newIdentity -&gt; INFO 008 Creating identity instance for ID &amp;{{DEFAULT} ROOTCA}\n18:15:02.731 [msp] newSigningIdentity -&gt; INFO 009 Creating signing identity instance for ID &amp;{{DEFAULT} PEER}\n18:15:02.731 [msp] Setup -&gt; INFO 00a MSP manager setup complete (config file \/opt\/gopath\/src\/github.com\/hyperledger\/fabric\/msp\/peer-config.json)\nError: Error getting chaincode code chaincode: Error getting chaincode package bytes: Cannot collect files from empty chaincode path\nUsage:\n...",
        "ts": "1481048181.000118"
    },
    {
        "type": "message",
        "user": "U0ULK2JPP",
        "text": "let me try it real quick",
        "ts": "1481048202.000119"
    },
    {
        "type": "message",
        "user": "U1ES70KQS",
        "text": "I was getting a different error with another chaincode I was working on, which I can run and get the error for if that'll be helpful",
        "ts": "1481048285.000120"
    },
    {
        "type": "message",
        "user": "U0ULK2JPP",
        "text": "hmm worked for me",
        "ts": "1481048404.000121"
    },
    {
        "type": "message",
        "user": "U0ULK2JPP",
        "text": "weird",
        "ts": "1481048406.000122"
    },
    {
        "type": "message",
        "user": "U0ULK2JPP",
        "text": "let me paste my command lines",
        "ts": "1481048413.000123"
    },
    {
        "type": "message",
        "user": "U1ES70KQS",
        "text": "I always seem to run into this sort of thing :smile:",
        "ts": "1481048417.000124"
    },
    {
        "type": "message",
        "user": "U0ULK2JPP",
        "text": "`peer node start --peer-chaincodedev`",
        "ts": "1481048431.000125"
    },
    {
        "type": "message",
        "user": "U0ULK2JPP",
        "text": "`CORE_CHAINCODE_ID_NAME=mycc CORE_PEER_ADDRESS=0.0.0.0:7051 .\/chaincode_example02`",
        "ts": "1481048449.000126"
    },
    {
        "type": "message",
        "user": "U1ES70KQS",
        "text": "also, quick question, how do I exit out of the peer? Ctrl+C doesn't seem to be quitting it",
        "ts": "1481048450.000127"
    },
    {
        "type": "message",
        "user": "U0ULK2JPP",
        "text": "`CORE_CHAINCODE_MODE=dev peer chaincode deploy -n mycc -c '{\"Args\":[\"init\",\"a\",\"100\",\"b\",\"200\"]}\u2019`",
        "ts": "1481048484.000128"
    },
    {
        "type": "message",
        "user": "U0ULK2JPP",
        "text": "that q. makes me wonder...",
        "ts": "1481048493.000129"
    },
    {
        "type": "message",
        "user": "U0ULK2JPP",
        "text": "hang on",
        "ts": "1481048497.000130"
    },
    {
        "type": "message",
        "user": "U0ULK2JPP",
        "text": "let me try one more thing",
        "ts": "1481048501.000131"
    },
    {
        "type": "message",
        "user": "U1ES70KQS",
        "text": "ok",
        "ts": "1481048514.000132"
    },
    {
        "type": "message",
        "user": "U1ES70KQS",
        "text": "my peer was emitting this error too, if that helps:",
        "ts": "1481048525.000133"
    },
    {
        "type": "message",
        "user": "U1ES70KQS",
        "text": "18:12:52.066 [nodeCmd] serve -&gt; INFO 05e Starting peer with ID=name:\"jdoe\" , network ID=dev, address=0.0.0.0:7051, rootnodes=, validator=true\n18:12:52.070 [committer] startDeliver -&gt; INFO 05f Starting deliver service client\n18:12:52.075 [comm--1] serviceConnection -&gt; WARN 060 [Closing reading from stream]\n18:12:52.075 [comm--1] func1 -&gt; WARN 061 [0.0.0.0:7051, PKIid:[] isn't responsive: rpc error: code = 13 desc = transport: write tcp 127.0.0.1:47848-&gt;127.0.0.1:7051: use of closed network connection]\n18:12:52.076 [comm--1] readFromStream -&gt; WARN 062 [[48 46 48 46 48 46 48 58 55 48 53 49] Got error, aborting: EOF]\n18:12:52.076 [comm--1] writeToStream -&gt; WARN 063 [Closing writing to stream]\n18:12:55.071 [committer] initDeliver -&gt; ERRO 064 Cannot dial to 0.0.0.0:7050, because of grpc: timed out when dialing\n18:12:55.071 [committer] startDeliver -&gt; ERRO 065 Can't initiate deliver protocol [grpc: timed out when dialing]\n18:13:02.132 [GossipStateProvider] antiEntropy -&gt; DEBU 066 Current ledger height is the same as ledger height on other peers.",
        "ts": "1481048526.000134"
    },
    {
        "type": "message",
        "user": "U0ULK2JPP",
        "text": "so",
        "ts": "1481048540.000135"
    },
    {
        "type": "message",
        "user": "U1ES70KQS",
        "text": "(two grpc errors, 2nd and 3rd to last lines)",
        "ts": "1481048544.000136"
    },
    {
        "type": "message",
        "user": "U0ULK2JPP",
        "text": "you are not running the orderer",
        "ts": "1481048546.000137"
    },
    {
        "type": "message",
        "user": "U0ULK2JPP",
        "text": "in another vagrant ssh",
        "ts": "1481048558.000138"
    },
    {
        "type": "message",
        "user": "U1ES70KQS",
        "text": "mmmm",
        "ts": "1481048563.000139"
    },
    {
        "type": "message",
        "user": "U0ULK2JPP",
        "text": "cd orderer",
        "ts": "1481048564.000140"
    },
    {
        "type": "message",
        "user": "U0ULK2JPP",
        "text": "go build",
        "ts": "1481048566.000141"
    },
    {
        "type": "message",
        "user": "U0ULK2JPP",
        "text": ".\/orderer",
        "ts": "1481048568.000142"
    },
    {
        "type": "message",
        "user": "U0ULK2JPP",
        "text": "then start the peer, chaincode \u2026",
        "ts": "1481048584.000143"
    },
    {
        "type": "message",
        "user": "U1ES70KQS",
        "text": "I don't recall seeing that in the documentation I was following",
        "ts": "1481048590.000144"
    },
    {
        "type": "message",
        "user": "U0ULK2JPP",
        "text": "and your deploy with the env should work",
        "ts": "1481048595.000145"
    },
    {
        "type": "message",
        "user": "U1ES70KQS",
        "text": "ok, let me try that",
        "ts": "1481048600.000146"
    },
    {
        "type": "message",
        "user": "U0ULK2JPP",
        "text": "not sure which doc you are looking at",
        "ts": "1481048602.000147"
    },
    {
        "type": "message",
        "user": "U1ES70KQS",
        "text": "<https:\/\/github.com\/hyperledger\/fabric\/blob\/master\/docs\/Setup\/Chaincode-setup.md>",
        "attachments": [
            {
                "service_name": "GitHub",
                "title": "hyperledger\/fabric",
                "title_link": "https:\/\/github.com\/hyperledger\/fabric\/blob\/master\/docs\/Setup\/Chaincode-setup.md",
                "text": "Read-only mirror of <https:\/\/gerrit.hyperledger.org\/r\/#\/admin\/projects\/fabric>",
                "fallback": "GitHub: hyperledger\/fabric",
                "thumb_url": "https:\/\/avatars3.githubusercontent.com\/u\/7657900?v=3&s=400",
                "from_url": "https:\/\/github.com\/hyperledger\/fabric\/blob\/master\/docs\/Setup\/Chaincode-setup.md",
                "thumb_width": 142,
                "thumb_height": 142,
                "service_icon": "https:\/\/github.com\/apple-touch-icon.png",
                "id": 1
            }
        ],
        "ts": "1481048616.000148"
    },
    {
        "type": "message",
        "user": "U1ES70KQS",
        "text": "probably outdated",
        "ts": "1481048622.000150"
    },
    {
        "type": "message",
        "user": "U0ULK2JPP",
        "text": "very much so",
        "ts": "1481048628.000151"
    },
    {
        "type": "message",
        "user": "U0ULK2JPP",
        "text": "that;s 0.6",
        "ts": "1481048633.000152"
    },
    {
        "type": "message",
        "user": "U0ULK2JPP",
        "text": "not much doc for master yet",
        "ts": "1481048638.000153"
    },
    {
        "type": "message",
        "user": "U0ULK2JPP",
        "text": "but there is are some instructions",
        "ts": "1481048647.000154"
    },
    {
        "type": "message",
        "user": "U0ULK2JPP",
        "text": "<https:\/\/wiki.hyperledger.org\/community\/fabric-design-docs> \u2026 look at the last link on running end-to-end",
        "ts": "1481048705.000155"
    },
    {
        "type": "message",
        "user": "U1ES70KQS",
        "text": "ah, thanks",
        "ts": "1481048755.000156"
    },
    {
        "type": "message",
        "user": "U1ES70KQS",
        "text": "order started, but peer gives me this error:",
        "ts": "1481048766.000157"
    },
    {
        "type": "message",
        "user": "U1ES70KQS",
        "text": "18:24:45.740 [protoutils] validateChainHeader -&gt; INFO 062 validateChainHeader info: header type 1\n18:24:45.740 [committer] readUntilClose -&gt; ERRO 063 Invalid transaction, error Invalid creator specified in the header",
        "ts": "1481048767.000158"
    },
    {
        "type": "message",
        "user": "U0ULK2JPP",
        "text": "that\u2019s ok",
        "ts": "1481048779.000159"
    },
    {
        "type": "message",
        "user": "U0ULK2JPP",
        "text": "ignore the first one",
        "ts": "1481048782.000160"
    },
    {
        "type": "message",
        "user": "U1ES70KQS",
        "text": "and still getting same error on deploy",
        "ts": "1481048791.000161"
    },
    {
        "type": "message",
        "user": "U0ULK2JPP",
        "text": "are you on latest ?",
        "ts": "1481048818.000162"
    },
    {
        "type": "message",
        "user": "U1ES70KQS",
        "text": "are you referring to documentation?",
        "ts": "1481048842.000163"
    },
    {
        "type": "message",
        "user": "U0ULK2JPP",
        "text": "I meant the master\u2026 when did you pull last ?",
        "ts": "1481048896.000164"
    },
    {
        "type": "message",
        "user": "U1ES70KQS",
        "text": "hour or two ago",
        "ts": "1481048984.000165"
    },
    {
        "type": "message",
        "user": "U1ES70KQS",
        "text": "I can re-pull and rebuild if you think that'd help",
        "ts": "1481048997.000166"
    },
    {
        "type": "message",
        "user": "U0ULK2JPP",
        "text": "no, that should be fine",
        "ts": "1481049024.000167"
    },
    {
        "type": "message",
        "user": "U3ADJU5MZ",
        "text": "<@U1ES70KQS>  i am also stuck at the same issue !",
        "ts": "1481049063.000168"
    },
    {
        "type": "message",
        "user": "U1ES70KQS",
        "text": "glad it's not just me!",
        "edited": {
            "user": "U1ES70KQS",
            "ts": "1481049100.000000"
        },
        "ts": "1481049088.000169"
    },
    {
        "type": "message",
        "user": "U0ULK2JPP",
        "text": "oops .. `CORE_CHAINCODE_MODE=dev`",
        "ts": "1481049171.000171"
    },
    {
        "type": "message",
        "user": "U1ES70KQS",
        "text": "<@U3ADJU5MZ> I'm looking at the end-to-end docs that muralisr just linked me to: <https:\/\/jira.hyperledger.org\/secure\/attachment\/10242\/simple_test_with_skeletal_peer.md>",
        "ts": "1481049179.000172"
    },
    {
        "type": "message",
        "user": "U0ULK2JPP",
        "text": "not `PEER_CHAINCODE_MODE=dev`",
        "ts": "1481049181.000173"
    },
    {
        "type": "message",
        "user": "U1ES70KQS",
        "text": "ah, let me try that",
        "ts": "1481049192.000174"
    },
    {
        "type": "message",
        "user": "U1ES70KQS",
        "text": "that worked!",
        "ts": "1481049212.000175"
    },
    {
        "type": "message",
        "user": "U0ULK2JPP",
        "text": "not that the end-to-end is not for \u201c\u2014peer-chaincodedev\"",
        "ts": "1481049223.000176"
    },
    {
        "type": "message",
        "user": "U0ULK2JPP",
        "text": "that mode has a gotcha",
        "ts": "1481049232.000177"
    },
    {
        "type": "message",
        "user": "U0ULK2JPP",
        "text": "after successful endorsement the chaincode is deregistered by the endorser pending later commit",
        "ts": "1481049261.000178"
    },
    {
        "type": "message",
        "user": "U0ULK2JPP",
        "text": "in non dev mode, the chaincode wil be broight up when you do an invoke",
        "ts": "1481049277.000179"
    },
    {
        "type": "message",
        "user": "U0ULK2JPP",
        "text": "but in `\u2014peer-chaincodedev` mode, after successful commit you\u2019ll have to kill the chaincode and restart it",
        "ts": "1481049310.000180"
    },
    {
        "type": "message",
        "user": "U0ULK2JPP",
        "text": "will likely be fixed at some point that `\u2014peer-chaincodedev` mode does the right thing for dev mode (basically not deregister but let it stay)",
        "ts": "1481049364.000181"
    },
    {
        "type": "message",
        "user": "U1ES70KQS",
        "text": "weird",
        "ts": "1481049364.000182"
    },
    {
        "type": "message",
        "user": "U0ULK2JPP",
        "text": "for now you have kill\/restart chaincode",
        "ts": "1481049380.000183"
    },
    {
        "type": "message",
        "user": "U1ES70KQS",
        "text": "so i have to invoke the deploy, then kill the chaincode, then restart it",
        "ts": "1481049391.000184"
    },
    {
        "type": "message",
        "user": "U0ULK2JPP",
        "text": "yea",
        "ts": "1481049408.000185"
    },
    {
        "type": "message",
        "user": "U0ULK2JPP",
        "text": "and invoke\/query will work",
        "ts": "1481049418.000186"
    },
    {
        "type": "message",
        "user": "U1ES70KQS",
        "text": "that is odd",
        "ts": "1481049434.000187"
    },
    {
        "type": "message",
        "user": "U1ES70KQS",
        "text": "I'll give it a shot; thank you very much for your help!",
        "ts": "1481049507.000188"
    },
    {
        "type": "message",
        "user": "U0ULK2JPP",
        "text": "anytime",
        "ts": "1481049517.000189"
    },
    {
        "type": "message",
        "user": "U0ULK2JPP",
        "text": "do try without \u2014peer-chaincodedev mode too",
        "ts": "1481049537.000190"
    },
    {
        "type": "message",
        "user": "U1ES70KQS",
        "text": "I will -- I have to give it the path for the deploy command then too, correct?",
        "ts": "1481049556.000191"
    },
    {
        "type": "message",
        "user": "U3ADJU5MZ",
        "text": "i did ... it gives the same error",
        "ts": "1481049559.000192"
    },
    {
        "type": "message",
        "user": "U0ULK2JPP",
        "text": "<@U1ES70KQS> yes in non-dev, you have to provide path",
        "ts": "1481049790.000193"
    },
    {
        "type": "message",
        "user": "U1ES70KQS",
        "text": "<@U3ADJU5MZ> are you running the orderer?",
        "ts": "1481049820.000194"
    },
    {
        "type": "message",
        "user": "U3ADJU5MZ",
        "text": "its tyring to connect to it and fails :confused:",
        "ts": "1481049853.000195"
    },
    {
        "type": "message",
        "user": "U3ADJU5MZ",
        "text": "so its not running i suppose",
        "ts": "1481049861.000196"
    },
    {
        "type": "message",
        "user": "U3ADJU5MZ",
        "text": "it keeps saying this \n```18:44:39.492 [committer] initDeliver -&gt; ERRO 067 Cannot dial to 0.0.0.0:7050, because of grpc: timed out when dialing\n18:44:39.493 [committer] startDeliver -&gt; ERRO 068 Can't initiate deliver protocol [grpc: timed out when dialing]```",
        "ts": "1481049897.000197"
    },
    {
        "type": "message",
        "user": "U1ES70KQS",
        "text": "yeah, that's what I was getting before muralisr pointed me to the orderer",
        "ts": "1481049916.000198"
    },
    {
        "type": "message",
        "user": "U1ES70KQS",
        "text": "do:",
        "ts": "1481049920.000199"
    },
    {
        "type": "message",
        "user": "U1ES70KQS",
        "text": "`fabric$ cd orderer`",
        "ts": "1481049935.000200"
    },
    {
        "type": "message",
        "user": "U1ES70KQS",
        "text": "`orderer$ go build`",
        "ts": "1481049944.000201"
    },
    {
        "type": "message",
        "user": "U1ES70KQS",
        "text": "`orderer$ .\/orderer`",
        "edited": {
            "user": "U1ES70KQS",
            "ts": "1481049964.000000"
        },
        "ts": "1481049956.000202"
    },
    {
        "type": "message",
        "user": "U1ES70KQS",
        "text": "then start the peer and you shouldn't have those grpc errors (though I did have another one)",
        "ts": "1481049982.000204"
    },
    {
        "type": "message",
        "user": "U3ADJU5MZ",
        "text": "i think this is what you are seeing `18:46:53.651 [committer] readUntilClose -&gt; ERRO 06b Invalid transaction, error Invalid creator specified in the header`",
        "ts": "1481050068.000205"
    },
    {
        "type": "message",
        "user": "U1ES70KQS",
        "text": "yup",
        "ts": "1481050113.000206"
    },
    {
        "type": "message",
        "user": "U1ES70KQS",
        "text": "worked for me after that (even with that Invalid transaction error)",
        "ts": "1481050160.000207"
    },
    {
        "type": "message",
        "user": "U3ADJU5MZ",
        "text": "hmmm ... let me also check !",
        "ts": "1481050185.000208"
    },
    {
        "type": "message",
        "user": "U3ADJU5MZ",
        "text": "<@U1ES70KQS>  work for me too :smile: ... finally !",
        "ts": "1481050460.000209"
    },
    {
        "type": "message",
        "user": "U1ES70KQS",
        "text": "awesome!",
        "ts": "1481050482.000210"
    },
    {
        "type": "message",
        "user": "U0ULK2JPP",
        "text": "<@U1ES70KQS> <@U3ADJU5MZ> just FYI,  if u kill orderer first, you cannot Ctrl-C on peer (you have to do a kill -9 &lt;peer\u2019s pid&gt;) \u2026 there\u2019s  CR out there that\u2019ll fix it",
        "ts": "1481050556.000211"
    },
    {
        "type": "message",
        "user": "U0ULK2JPP",
        "text": "but if you kill peer first, ctrl-c will work",
        "ts": "1481050569.000212"
    },
    {
        "type": "message",
        "user": "U1ES70KQS",
        "text": "thanks muralisr",
        "ts": "1481050601.000213"
    },
    {
        "type": "message",
        "user": "U1ES70KQS",
        "text": "and thanks again for all your help!",
        "ts": "1481050607.000214"
    },
    {
        "type": "message",
        "user": "U3ADJU5MZ",
        "text": "<@U0ULK2JPP>  i am using `peer node stop` to stop the peer",
        "ts": "1481050639.000215"
    },
    {
        "type": "message",
        "user": "U0ULK2JPP",
        "text": "not tried that with master honestly",
        "ts": "1481050673.000216"
    },
    {
        "type": "message",
        "user": "U1ES70KQS",
        "text": "it seems I have to specify a name when specifying a path still? I though the name would be assigned automatically and returned",
        "ts": "1481050899.000217"
    },
    {
        "type": "message",
        "user": "U3ADJU5MZ",
        "text": "yup",
        "ts": "1481051015.000218"
    },
    {
        "type": "message",
        "user": "U0ULK2JPP",
        "text": "<@U1ES70KQS> the automatic assignment is gone in 1.0 \u2026 the name you specify is the unique one used by fabric",
        "ts": "1481051496.000219"
    },
    {
        "type": "message",
        "user": "U0ULK2JPP",
        "text": "long story short \u2026 as we have the luxury of \u201clife cycle system chaincode\u201d we can do these things",
        "ts": "1481051560.000220"
    },
    {
        "type": "message",
        "user": "U3ADJU5MZ",
        "text": "<@U0ULK2JPP>  my orderer crashes with `panic` when I try to deploy my chaincode with `peer chaincode deploy -C mycc -n mycc -c '{\"Args\": [\"init\", \"a\",\"100\", \"b\", \"200\"]}' -p <http:\/\/github.com\/hyperledger\/fabric\/examples\/chaincode\/go\/chaincode_example02|github.com\/hyperledger\/fabric\/examples\/chaincode\/go\/chaincode_example02>`",
        "ts": "1481051608.000221"
    },
    {
        "type": "message",
        "user": "U0ULK2JPP",
        "text": "currently the orderer does not yet support \u201cmultichains\"",
        "ts": "1481051674.000222"
    },
    {
        "type": "message",
        "user": "U0ULK2JPP",
        "text": "I\u2019d not use the \u201c-C\u201d option yet",
        "ts": "1481051692.000223"
    },
    {
        "type": "message",
        "user": "U3ADJU5MZ",
        "text": "okay let me try without that",
        "ts": "1481051707.000224"
    },
    {
        "type": "message",
        "user": "U0ULK2JPP",
        "text": "the fabric defaults to a chain called **TEST_CHAINID**",
        "ts": "1481051716.000225"
    },
    {
        "type": "message",
        "user": "U0ULK2JPP",
        "text": "which you dont\u2019 have to provide",
        "ts": "1481051724.000226"
    },
    {
        "type": "message",
        "user": "U3ADJU5MZ",
        "text": "yeah it see that in the `\/var\/hyperledger\/ledger` folder",
        "ts": "1481051802.000227"
    },
    {
        "type": "message",
        "user": "U0ULK2JPP",
        "text": "yes",
        "ts": "1481051815.000228"
    },
    {
        "type": "message",
        "user": "U3ADJU5MZ",
        "text": "well this `peer chaincode -n mycc query -c '{\"Args\": [\"query\", \"b\"]}' -p <http:\/\/github.com\/hyperledger\/fabric\/examples\/chaincode\/go\/chaincode_example02|github.com\/hyperledger\/fabric\/examples\/chaincode\/go\/chaincode_example02>` doesn't work for me",
        "ts": "1481051917.000229"
    },
    {
        "type": "message",
        "user": "U3ADJU5MZ",
        "text": "it deploys the chaincode fine but throws error on that",
        "ts": "1481051946.000230"
    },
    {
        "type": "message",
        "user": "U3ADJU5MZ",
        "text": "error says `Error: Error endorsing chaincode: rpc error: code = 2 desc = Error deploying chaincode: Failed to launch chaincode spec(Failed to init chaincode(handler not found for chaincode mycc))`",
        "ts": "1481051965.000231"
    },
    {
        "type": "message",
        "user": "U0ULK2JPP",
        "text": "give it 10 seconds and try again",
        "ts": "1481051970.000232"
    },
    {
        "type": "message",
        "user": "U3ADJU5MZ",
        "text": "ooh",
        "ts": "1481051979.000233"
    },
    {
        "type": "message",
        "user": "U0ULK2JPP",
        "text": "the orderers default configuration is to wait 10 seconds to batch up all transactions to order",
        "ts": "1481052014.000234"
    },
    {
        "type": "message",
        "user": "U0ULK2JPP",
        "text": "typically I wait to see the \u201cCommit\u201d message on the peer console before I send querie",
        "ts": "1481052038.000235"
    },
    {
        "type": "message",
        "user": "U3ADJU5MZ",
        "text": "<@U0ULK2JPP>  its still giving the same error",
        "ts": "1481052742.000236"
    },
    {
        "type": "message",
        "user": "U3ADJU5MZ",
        "text": "i was able to get `19:29:35.377 [GossipStateProvider] commitBlock -&gt; DEBU 136 [XXX]: Commit success, created a block!`",
        "ts": "1481052755.000237"
    },
    {
        "type": "message",
        "user": "U3ADJU5MZ",
        "text": "but even after that the query  doesn't work",
        "ts": "1481052777.000238"
    },
    {
        "type": "message",
        "user": "U3ADJU5MZ",
        "text": "peer console says : `19:30:34.494 [chaincode] Launch -&gt; ERRO 14d You are attempting to perform an action other than Deploy on Chaincode that is not ready and you are in developer mode. Did you forget to Deploy your chaincode?`",
        "ts": "1481052799.000239"
    },
    {
        "type": "message",
        "user": "U3ADJU5MZ",
        "text": "`19:30:34.544 [chaincode] Launch -&gt; ERRO 162 sending init failed(handler not found for chaincode mycc)`",
        "ts": "1481052826.000240"
    },
    {
        "type": "message",
        "user": "U3ADJU5MZ",
        "text": "wow ... it worked for some reason !",
        "ts": "1481053295.000241"
    },
    {
        "type": "message",
        "user": "U3ADJU5MZ",
        "text": "i don't know how :confused:",
        "ts": "1481053318.000242"
    },
    {
        "type": "message",
        "user": "U3ADJU5MZ",
        "text": "typical developer's dilemma !",
        "ts": "1481053352.000243"
    },
    {
        "type": "message",
        "user": "U3ADJU5MZ",
        "text": "to anyone who hits this situation, I just restart the chaincode and it worked !",
        "ts": "1481053651.000244"
    },
    {
        "type": "message",
        "user": "U1ES70KQS",
        "text": "is this documentation still current or is there a different way to run chaincode invocations via REST?",
        "ts": "1481055856.000246"
    },
    {
        "type": "message",
        "user": "U1ES70KQS",
        "text": "<https:\/\/github.com\/hyperledger\/fabric\/blob\/master\/docs\/Setup\/Chaincode-setup.md#chaincode-invoke-via-cli-and-rest>",
        "attachments": [
            {
                "service_name": "GitHub",
                "title": "hyperledger\/fabric",
                "title_link": "https:\/\/github.com\/hyperledger\/fabric\/blob\/master\/docs\/Setup\/Chaincode-setup.md#chaincode-invoke-via-cli-and-rest",
                "text": "Read-only mirror of <https:\/\/gerrit.hyperledger.org\/r\/#\/admin\/projects\/fabric>",
                "fallback": "GitHub: hyperledger\/fabric",
                "thumb_url": "https:\/\/avatars3.githubusercontent.com\/u\/7657900?v=3&s=400",
                "from_url": "https:\/\/github.com\/hyperledger\/fabric\/blob\/master\/docs\/Setup\/Chaincode-setup.md#chaincode-invoke-via-cli-and-rest",
                "thumb_width": 142,
                "thumb_height": 142,
                "service_icon": "https:\/\/github.com\/apple-touch-icon.png",
                "id": 1
            }
        ],
        "ts": "1481055857.000247"
    },
    {
        "user": "U35FGUMN0",
        "text": "<@U35FGUMN0|walker> has joined the channel",
        "type": "message",
        "subtype": "channel_join",
        "ts": "1481061322.000250"
    },
    {
        "type": "message",
        "user": "U2X9KDDL7",
        "text": "Hi all, are there specifications as to the runtime complexity of the various ledger state\/table operations?",
        "ts": "1481067123.000251"
    },
    {
        "user": "U3BKSKKPF",
        "text": "<@U3BKSKKPF|yevot> has joined the channel",
        "type": "message",
        "subtype": "channel_join",
        "ts": "1481082077.000259"
    },
    {
        "type": "message",
        "user": "U3ADJU5MZ",
        "text": "<@U1ES70KQS>  I have been tyring to locate the REST server in fabric code but haven't been successfull yet.",
        "ts": "1481091915.000262"
    },
    {
        "type": "message",
        "user": "U3ADJU5MZ",
        "text": "if anyone knows where the server code is located at then please point me in that direction",
        "ts": "1481091960.000263"
    },
    {
        "type": "message",
        "user": "U2X9KDDL7",
        "text": "In branch v0.6 it's at <https:\/\/github.com\/hyperledger\/fabric\/tree\/v0.6\/core\/rest> -- the REST API has been deprecated in v1.0 (master branch).. maybe it's been removed altogether by now",
        "attachments": [
            {
                "service_name": "GitHub",
                "title": "hyperledger\/fabric",
                "title_link": "https:\/\/github.com\/hyperledger\/fabric\/tree\/v0.6\/core\/rest",
                "text": "Read-only mirror of <https:\/\/gerrit.hyperledger.org\/r\/#\/admin\/projects\/fabric>",
                "fallback": "GitHub: hyperledger\/fabric",
                "thumb_url": "https:\/\/avatars3.githubusercontent.com\/u\/7657900?v=3&s=400",
                "from_url": "https:\/\/github.com\/hyperledger\/fabric\/tree\/v0.6\/core\/rest",
                "thumb_width": 142,
                "thumb_height": 142,
                "service_icon": "https:\/\/github.com\/apple-touch-icon.png",
                "id": 1
            }
        ],
        "ts": "1481095684.000266"
    },
    {
        "type": "message",
        "user": "U3ADJU5MZ",
        "text": "yeah seems like it ... i am looking at the node sdk to find out how to talk to fabric",
        "ts": "1481095775.000268"
    },
    {
        "user": "U1934J6RX",
        "text": "<@U1934J6RX|iamsamwood> has joined the channel",
        "type": "message",
        "subtype": "channel_join",
        "ts": "1481095981.000269"
    },
    {
        "type": "message",
        "user": "U2X9KDDL7",
        "text": "The preferred protocol is now GRPC, which is good because it seems like far superior to REST, where you'd have to serialize\/deserialize the API calls yourself",
        "ts": "1481096074.000270"
    },
    {
        "type": "message",
        "user": "U2X9KDDL7",
        "text": "v0.6 and v1.0 both can use GRPC, so it seems like a no-lose situation going with GRPC",
        "ts": "1481096096.000271"
    },
    {
        "type": "message",
        "user": "U1934J6RX",
        "text": "<@U2X9KDDL7> I thought v0.6 only supported json RPC? did a minor version bring that in ?",
        "ts": "1481096283.000272"
    },
    {
        "type": "message",
        "user": "U2X9KDDL7",
        "text": "As far as I can tell, HFC interacts with the membersrvc, peer, and event hub entirely via GRPC",
        "ts": "1481096411.000273"
    },
    {
        "type": "message",
        "user": "U2X9KDDL7",
        "text": "v0.6",
        "ts": "1481096420.000274"
    },
    {
        "user": "U3AU6D7L1",
        "text": "<@U3AU6D7L1|voritic> has joined the channel",
        "type": "message",
        "subtype": "channel_join",
        "ts": "1481096485.000275"
    },
    {
        "type": "message",
        "user": "U3BKSKKPF",
        "text": "I'm on v0.6 and mainly using REST. Is there a way I can add arbitrary key, value pairs to the blocks\/transactions?",
        "ts": "1481096723.000276"
    },
    {
        "type": "message",
        "user": "U2T7Z63NY",
        "text": "I have setup Hyper ledger v 0.6. Now, while executing Invoke() method of sample application \"authorizable_counter\"  with REST call, we encounter \"Failed retrieving extension\". Did someone face similar issue?\n\nThanks.",
        "edited": {
            "user": "U2T7Z63NY",
            "ts": "1481097563.000000"
        },
        "ts": "1481097474.000277"
    }
]