[
    {
        "user": "U19GFUXD5",
        "type": "message",
        "subtype": "channel_join",
        "text": "<@U19GFUXD5|dneary> has joined the channel",
        "ts": "1463493433.000197"
    },
    {
        "type": "message",
        "user": "U19GFUXD5",
        "text": "Hi, Mike Dolan just pointed me here - and I got some of the answers to some of the questions I had from browsing the last couple of weeks of chat.",
        "ts": "1463493469.000198",
        "reactions": [
            {
                "name": "+1",
                "users": [
                    "U0KM61BCP"
                ],
                "count": 1
            }
        ]
    },
    {
        "type": "message",
        "user": "U1113R4D6",
        "text": "oleg where are you in moscow?",
        "ts": "1463514510.000199"
    },
    {
        "type": "message",
        "user": "U0ULQ2G5V",
        "text": "<@U1113R4D6>: I'm based in NY. Stuart, would you be interested in developing  a use case doc for Hyperledger?  Trading in unlisted securities?",
        "ts": "1463515333.000200"
    },
    {
        "type": "message",
        "user": "U1113R4D6",
        "text": "yes",
        "ts": "1463515926.000201"
    },
    {
        "user": "U19P51JUR",
        "type": "message",
        "subtype": "channel_join",
        "text": "<@U19P51JUR|akash> has joined the channel",
        "ts": "1463544688.000202"
    },
    {
        "user": "U19MP2N67",
        "type": "message",
        "subtype": "channel_join",
        "text": "<@U19MP2N67|rupendradhillon> has joined the channel",
        "ts": "1463547454.000203"
    }
]