[
    {
        "type": "message",
        "user": "U0UHG4VP1",
        "text": "hgabor: I see that but I want to wait for everything else to fail or succeed before messing with anything",
        "ts": "1471330815.000141"
    },
    {
        "type": "message",
        "user": "U0UHG4VP1",
        "text": "hgabor: it\u2019s also midnight and I need dinner, so I will go eat and attack these problems in the morning",
        "ts": "1471330848.000142"
    },
    {
        "type": "message",
        "user": "U1AU8DRQR",
        "text": "okay",
        "ts": "1471330981.000143"
    },
    {
        "type": "message",
        "user": "U1AU8DRQR",
        "text": "I guess maybe mvn got removed somehow",
        "ts": "1471331012.000144"
    },
    {
        "type": "message",
        "user": "U1AU8DRQR",
        "text": "maven",
        "ts": "1471331016.000145"
    },
    {
        "type": "message",
        "user": "U0UHG4VP1",
        "text": "I had to rebuild the vagrant stuff, it is possible I missed something. that is to say, that I built the builder stuff on the wrong source image. there were two images.",
        "ts": "1471331075.000146"
    },
    {
        "type": "message",
        "user": "U0UHG4VP1",
        "text": "looking here, some of the builds failed for strange reasons (unsigned ppa) and some look like they are working: <https:\/\/jenkins.hyperledger.org\/job\/fabric-verify-x86_64\/buildTimeTrend>",
        "ts": "1471331138.000147"
    },
    {
        "type": "message",
        "user": "U1M7K67EV",
        "text": "<@U0UHG4VP1> I've seen that unsigned failure before because the PPA where Java8 is sourced from fails to get the GPG key because of downtime on the other server or something similar.",
        "ts": "1471331348.000148"
    },
    {
        "type": "message",
        "user": "U1M7K67EV",
        "text": "If we moved to a 16.04 image then we'd be able to get it from the stock ubuntu repos but I wouldn't know the first place to start doing that",
        "ts": "1471331386.000149"
    },
    {
        "type": "message",
        "user": "U0UHG4VP1",
        "text": "jcarrivick: interesting. this really hit us at a weak moment - it was a huge failure at our ISP, on a weekend, when a key person is on vacation :disappointed:",
        "ts": "1471331465.000150"
    },
    {
        "type": "message",
        "user": "U0UHG4VP1",
        "text": "I will comb the logs in the morning. I hope I can retrigger some of these builds and they\u2019ll Just Work, but who knows?",
        "ts": "1471331512.000151"
    },
    {
        "type": "message",
        "user": "U1M7K67EV",
        "text": "Yes go and enjoy some food and sleep - you've certainly earned it!",
        "ts": "1471331554.000152",
        "reactions": [
            {
                "name": "+1",
                "users": [
                    "U0UHG4VP1"
                ],
                "count": 1
            }
        ]
    },
    {
        "type": "message",
        "user": "U0KM61BCP",
        "text": "something I should probably know, how do we re-trigger Jenkins now?",
        "ts": "1471354214.000153"
    },
    {
        "type": "message",
        "subtype": "file_share",
        "text": "<@U11HH3P7Y|ramesh> uploaded a file: <https:\/\/hyperledgerproject.slack.com\/files\/ramesh\/F21R9NVRT\/capture.png|Capture.PNG> and commented: click on re-trigger button after selecting specific build",
        "file": {
            "id": "F21R9NVRT",
            "created": 1471354547,
            "timestamp": 1471354547,
            "name": "Capture.PNG",
            "title": "Capture.PNG",
            "mimetype": "image\/png",
            "filetype": "png",
            "pretty_type": "PNG",
            "user": "U11HH3P7Y",
            "editable": false,
            "size": 42159,
            "mode": "hosted",
            "is_external": false,
            "external_type": "",
            "is_public": true,
            "public_url_shared": false,
            "display_as_bot": false,
            "username": "",
            "url_private": "https:\/\/files.slack.com\/files-pri\/T0J024XGA-F21R9NVRT\/capture.png?t=xoxe-18002167554-139099126023-137701436192-e599afc92e",
            "url_private_download": "https:\/\/files.slack.com\/files-pri\/T0J024XGA-F21R9NVRT\/download\/capture.png?t=xoxe-18002167554-139099126023-137701436192-e599afc92e",
            "thumb_64": "https:\/\/files.slack.com\/files-tmb\/T0J024XGA-F21R9NVRT-0643d3821f\/capture_64.png?t=xoxe-18002167554-139099126023-137701436192-e599afc92e",
            "thumb_80": "https:\/\/files.slack.com\/files-tmb\/T0J024XGA-F21R9NVRT-0643d3821f\/capture_80.png?t=xoxe-18002167554-139099126023-137701436192-e599afc92e",
            "thumb_360": "https:\/\/files.slack.com\/files-tmb\/T0J024XGA-F21R9NVRT-0643d3821f\/capture_360.png?t=xoxe-18002167554-139099126023-137701436192-e599afc92e",
            "thumb_360_w": 151,
            "thumb_360_h": 360,
            "thumb_480": "https:\/\/files.slack.com\/files-tmb\/T0J024XGA-F21R9NVRT-0643d3821f\/capture_480.png?t=xoxe-18002167554-139099126023-137701436192-e599afc92e",
            "thumb_480_w": 201,
            "thumb_480_h": 480,
            "thumb_160": "https:\/\/files.slack.com\/files-tmb\/T0J024XGA-F21R9NVRT-0643d3821f\/capture_160.png?t=xoxe-18002167554-139099126023-137701436192-e599afc92e",
            "image_exif_rotation": 1,
            "original_w": 272,
            "original_h": 650,
            "permalink": "https:\/\/hyperledgerproject.slack.com\/files\/ramesh\/F21R9NVRT\/capture.png",
            "permalink_public": "https:\/\/slack-files.com\/T0J024XGA-F21R9NVRT-a3c430521e",
            "channels": [
                "C0YMWRX19"
            ],
            "groups": [],
            "ims": [],
            "comments_count": 1,
            "initial_comment": {
                "id": "Fc21R9PAQ5",
                "created": 1471354547,
                "timestamp": 1471354547,
                "user": "U11HH3P7Y",
                "is_intro": true,
                "comment": "click on re-trigger button after selecting specific build",
                "channel": ""
            },
            "reactions": [
                {
                    "name": "woo",
                    "users": [
                        "U0UHG4VP1"
                    ],
                    "count": 1
                }
            ]
        },
        "user": "U11HH3P7Y",
        "upload": true,
        "display_as_bot": false,
        "username": "<@U11HH3P7Y|ramesh>",
        "bot_id": null,
        "ts": "1471354550.000154"
    },
    {
        "type": "message",
        "user": "U1BC5NF2S",
        "text": "<@U0KM61BCP>: You should be able to comment 'reverify' on your patchset as well.",
        "ts": "1471356892.000155"
    }
]