[
    {
        "user": "U3M7LEDT4",
        "text": "<@U3M7LEDT4|david87> has joined the channel",
        "type": "message",
        "subtype": "channel_join",
        "ts": "1483544241.000047"
    },
    {
        "type": "message",
        "user": "U3M7LEDT4",
        "text": "Hi, does anybody know about the following problem? Its on 1.0.0-preview deploying a sample app  ```017-01-04 14:10:29.838 UTC [dockercontroller] deployImage -&gt; ERRO 464 Error building images: Tag x86_64-1.0.0-preview not found in repository <http:\/\/docker.io\/hyperledger\/fabric-ccenv|docker.io\/hyperledger\/fabric-ccenv>\n2017-01-04 14:10:29.838 UTC [dockercontroller] deployImage -&gt; ERRO 465 Image Output:\n********************\nStep 1 : FROM hyperledger\/fabric-ccenv:x86_64-1.0.0-preview\nPulling repository <http:\/\/docker.io\/hyperledger\/fabric-ccenv|docker.io\/hyperledger\/fabric-ccenv>\n\n********************```",
        "ts": "1483544549.000050"
    }
]