[
    {
        "type": "message",
        "user": "U0KM61BCP",
        "text": "<!channel>: <http:\/\/lists.hyperledger.org\/pipermail\/hyperledger-fabric\/2016-August\/000248.html>",
        "ts": "1471523407.001375"
    },
    {
        "type": "message",
        "user": "U0N13GKRP",
        "text": "Thanks for the heads up <@U0KM61BCP> ",
        "ts": "1471530403.001377"
    },
    {
        "type": "message",
        "user": "U0Z41KY5V",
        "text": "+1",
        "ts": "1471531302.001378"
    },
    {
        "type": "message",
        "user": "U11TAFPUP",
        "text": "Hi,",
        "ts": "1471536573.001379"
    },
    {
        "type": "message",
        "user": "U11TAFPUP",
        "text": "I run a fabric network with security and privacy enabled.",
        "ts": "1471536616.001380"
    },
    {
        "type": "message",
        "user": "U11TAFPUP",
        "text": "When I query a chaincode, it returns data that look like encrypted.",
        "ts": "1471536655.001381"
    },
    {
        "type": "message",
        "user": "U11TAFPUP",
        "text": "How can I do to decrypt that data?",
        "ts": "1471536717.001382"
    },
    {
        "user": "U147G4UTS",
        "text": "<@U147G4UTS|kalpatel> has joined the channel",
        "type": "message",
        "subtype": "channel_join",
        "ts": "1471542523.001384"
    },
    {
        "user": "U22MGCB35",
        "text": "<@U22MGCB35|kazuuu> has joined the channel",
        "type": "message",
        "subtype": "channel_join",
        "ts": "1471549105.001385"
    },
    {
        "type": "message",
        "user": "U1TA5FDU7",
        "text": "When I start 4 peers  by docker-compose... command, I got this error. Can anyone help me with it.  Any help would be appreciated !!\n[peer] handleChat -&gt; ERRO 072 Error handling message: Peer FSM failed while handling message (DISC_HELLO): current state: created, error: transition canceled with error: Error registering Handler: Duplicate Handler error: {name:\"vp1\"  172.17.0.4:30303 VALIDATOR }",
        "ts": "1471571324.001387"
    },
    {
        "user": "U20PAD7B4",
        "text": "<@U20PAD7B4|truc.nguyen> has joined the channel",
        "type": "message",
        "subtype": "channel_join",
        "ts": "1471577015.001389"
    },
    {
        "type": "message",
        "user": "U20PAD7B4",
        "text": "<@U11TAFPUP>  the result is hex-encoded.\ntx.on('complete', function (results) {\n   console.log('Results:[%j]', new Buffer(results,'hex').toString());\n}\nshould work",
        "attachments": [
            {
                "fallback": "[August 18th, 2016 11:11 PM] joseph: How can I do to decrypt that data?",
                "ts": "1471536717.001382",
                "author_subname": "joseph",
                "channel_id": "C0Y4PEU22",
                "channel_name": "fabric",
                "is_msg_unfurl": true,
                "text": "How can I do to decrypt that data?",
                "author_name": "tien nguyen",
                "author_link": "https:\/\/hyperledgerproject.slack.com\/team\/joseph",
                "author_icon": "https:\/\/secure.gravatar.com\/avatar\/791c6a3a1a8a62a76238b2b8eb1cf45c.jpg?s=48&d=https%3A%2F%2Fa.slack-edge.com%2F66f9%2Fimg%2Favatars%2Fava_0023-48.png",
                "mrkdwn_in": [
                    "text"
                ],
                "color": "D0D0D0",
                "from_url": "https:\/\/hyperledgerproject.slack.com\/archives\/fabric\/p1471536717001382",
                "is_share": true,
                "footer": "Posted in #fabric"
            }
        ],
        "edited": {
            "user": "U20PAD7B4",
            "ts": "1471577071.000000"
        },
        "ts": "1471577017.001390"
    }
]